{"timestamp": "Tue Aug 31 15:05:56 2021", "loosers": [{"ticker": "GSAT", "name": "Globalstar, Inc.", "change": "-14.89%"}, {"ticker": "AMC", "name": "AMC Entertainment Holdings, Inc.", "change": "+5.24%"}, {"ticker": "EDU", "name": "New Oriental Education & Technology Group Inc.", "change": "0.00%"}, {"ticker": "AAPL", "name": "Apple Inc.", "change": "-0.92%"}, {"ticker": "AMD", "name": "Advanced Micro Devices, Inc.", "change": "-1.74%"}, {"ticker": "ZM", "name": "Zoom Video Communications, Inc.", "change": "-15.39%"}, {"ticker": "NIO", "name": "NIO Inc.", "change": "+2.80%"}, {"ticker": "BAC", "name": "Bank of America Corporation", "change": "+0.70%"}, {"ticker": "PLTR", "name": "Palantir Technologies Inc.", "change": "+1.53%"}, {"ticker": "F", "name": "Ford Motor Company", "change": "-0.19%"}, {"ticker": "SPCE", "name": "Virgin Galactic Holdings, Inc.", "change": "+8.40%"}, {"ticker": "BABA", "name": "Alibaba Group Holding Limited", "change": "+3.23%"}, {"ticker": "CCL", "name": "Carnival Corporation & plc", "change": "+0.38%"}, {"ticker": "T", "name": "AT&T Inc.", "change": "+0.83%"}, {"ticker": "VEON", "name": "VEON Ltd.", "change": "-0.23%"}, {"ticker": "TAL", "name": "TAL Education Group", "change": "+1.88%"}, {"ticker": "CLF", "name": "Cleveland-Cliffs Inc.", "change": "-2.64%"}, {"ticker": "NVDA", "name": "NVIDIA Corporation", "change": "-1.78%"}, {"ticker": "PFE", "name": "Pfizer Inc.", "change": "-0.73%"}, {"ticker": "BBD", "name": "Banco Bradesco S.A.", "change": "+2.82%"}, {"ticker": "AAL", "name": "American Airlines Group Inc.", "change": "+0.64%"}, {"ticker": "OXY", "name": "Occidental Petroleum Corporation", "change": "+2.18%"}, {"ticker": "WISH", "name": "ContextLogic Inc.", "change": "+0.28%"}, {"ticker": "ITUB", "name": "Ita\u00fa Unibanco Holding S.A.", "change": "+3.59%"}, {"ticker": "TSLA", "name": "Tesla, Inc.", "change": "+1.14%"}]}