{"timestamp": "Tue May  4 17:26:36 2021", "loosers": [{"ticker": "AAPL", "name": "Apple Inc.", "change": "-4.08%"}, {"ticker": "OCGN", "name": "Ocugen, Inc.", "change": "-18.50%"}, {"ticker": "NIO", "name": "NIO Inc.", "change": "-4.74%"}, {"ticker": "PLTR", "name": "Palantir Technologies Inc.", "change": "-4.87%"}, {"ticker": "GE", "name": "General Electric Company", "change": "-2.49%"}, {"ticker": "F", "name": "Ford Motor Company", "change": "-2.24%"}, {"ticker": "NOK", "name": "Nokia Corporation", "change": "-4.89%"}, {"ticker": "AMD", "name": "Advanced Micro Devices, Inc.", "change": "-0.94%"}, {"ticker": "PFE", "name": "Pfizer Inc.", "change": "+0.35%"}, {"ticker": "BAC", "name": "Bank of America Corporation", "change": "+0.86%"}, {"ticker": "PLUG", "name": "Plug Power Inc.", "change": "-7.29%"}, {"ticker": "CLF", "name": "Cleveland-Cliffs Inc.", "change": "+9.64%"}, {"ticker": "X", "name": "United States Steel Corporation", "change": "+6.85%"}, {"ticker": "MVIS", "name": "MicroVision, Inc.", "change": "+15.66%"}, {"ticker": "ITUB", "name": "Ita\u00fa Unibanco Holding S.A.", "change": "-3.85%"}, {"ticker": "T", "name": "AT&T Inc.", "change": "+1.26%"}, {"ticker": "AMC", "name": "AMC Entertainment Holdings, Inc.", "change": "-5.41%"}, {"ticker": "AAL", "name": "American Airlines Group Inc.", "change": "-3.96%"}, {"ticker": "CCL", "name": "Carnival Corporation & plc", "change": "-5.17%"}, {"ticker": "SNAP", "name": "Snap Inc.", "change": "-8.81%"}, {"ticker": "TWTR", "name": "Twitter, Inc.", "change": "-1.06%"}, {"ticker": "INTC", "name": "Intel Corporation", "change": "-1.48%"}, {"ticker": "TSLA", "name": "Tesla, Inc.", "change": "-2.69%"}, {"ticker": "SKLZ", "name": "Skillz Inc.", "change": "+4.79%"}, {"ticker": "SABR", "name": "Sabre Corporation", "change": "-13.07%"}]}