{"timestamp": "Tue Jul 27 15:05:16 2021", "loosers": [{"ticker": "GE", "name": "General Electric Company", "change": "+1.15%"}, {"ticker": "TAL", "name": "TAL Education Group", "change": "+5.11%"}, {"ticker": "NIO", "name": "NIO Inc.", "change": "-8.20%"}, {"ticker": "AAPL", "name": "Apple Inc.", "change": "-1.34%"}, {"ticker": "BABA", "name": "Alibaba Group Holding Limited", "change": "-4.55%"}, {"ticker": "AMD", "name": "Advanced Micro Devices, Inc.", "change": "-0.94%"}, {"ticker": "AMC", "name": "AMC Entertainment Holdings, Inc.", "change": "-4.34%"}, {"ticker": "SIRI", "name": "Sirius XM Holdings Inc.", "change": "+5.80%"}, {"ticker": "BEKE", "name": "KE Holdings Inc.", "change": "-4.01%"}, {"ticker": "JD", "name": "JD.com, Inc.", "change": "-6.28%"}, {"ticker": "DIDI", "name": "DiDi Global Inc.", "change": "-2.49%"}, {"ticker": "CCIV", "name": "Lucid Group, Inc.", "change": "+5.90%"}, {"ticker": "GOTU", "name": "Gaotu Techedu Inc.", "change": "+4.76%"}, {"ticker": "XPEV", "name": "XPeng Inc.", "change": "-14.66%"}, {"ticker": "BAC", "name": "Bank of America Corporation", "change": "-0.17%"}, {"ticker": "SNAP", "name": "Snap Inc.", "change": "-4.01%"}, {"ticker": "INTC", "name": "Intel Corporation", "change": "-3.19%"}, {"ticker": "TSLA", "name": "Tesla, Inc.", "change": "-1.97%"}, {"ticker": "F", "name": "Ford Motor Company", "change": "-1.28%"}, {"ticker": "TME", "name": "Tencent Music Entertainment Group", "change": "-5.93%"}, {"ticker": "AAL", "name": "American Airlines Group Inc.", "change": "-2.72%"}, {"ticker": "CCL", "name": "Carnival Corporation & plc", "change": "-2.18%"}, {"ticker": "NOK", "name": "Nokia Corporation", "change": "-1.66%"}, {"ticker": "T", "name": "AT&T Inc.", "change": "+0.43%"}, {"ticker": "WISH", "name": "ContextLogic Inc.", "change": "-2.08%"}]}