{"timestamp": "Mon Feb 22 20:03:52 2021", "loosers": [{"ticker": "SNDL", "name": "Sundial Growers Inc.", "change": "-3.85%"}, {"ticker": "PBR", "name": "Petr\u00f3leo Brasileiro S.A. - Petrobras", "change": "-20.50%"}, {"ticker": "PLTR", "name": "Palantir Technologies Inc.", "change": "-2.60%"}, {"ticker": "AMC", "name": "AMC Entertainment Holdings, Inc.", "change": "+15.12%"}, {"ticker": "ITUB", "name": "Ita\u00fa Unibanco Holding S.A.", "change": "-7.89%"}, {"ticker": "AAL", "name": "American Airlines Group Inc.", "change": "+10.47%"}, {"ticker": "GE", "name": "General Electric Company", "change": "+4.24%"}, {"ticker": "AAPL", "name": "Apple Inc.", "change": "-2.19%"}, {"ticker": "CCL", "name": "Carnival Corporation & plc", "change": "+8.80%"}, {"ticker": "RLLCF", "name": "Rolls-Royce Holdings plc", "change": "-3.43%"}, {"ticker": "TSNP", "name": "Tesoro Enterprises, Inc.", "change": "+12.15%"}, {"ticker": "CCIV", "name": "Churchill Capital Corp IV", "change": "+13.16%"}, {"ticker": "BBD", "name": "Banco Bradesco S.A.", "change": "-7.21%"}, {"ticker": "NIO", "name": "NIO Limited", "change": "-6.21%"}, {"ticker": "F", "name": "Ford Motor Company", "change": "+2.63%"}, {"ticker": "NOK", "name": "Nokia Corporation", "change": "-1.97%"}, {"ticker": "RIOT", "name": "Riot Blockchain, Inc.", "change": "-7.03%"}, {"ticker": "BAC", "name": "Bank of America Corporation", "change": "+1.82%"}, {"ticker": "ZOM", "name": "Zomedica Corp.", "change": "-3.95%"}, {"ticker": "VALE", "name": "Vale S.A.", "change": "-3.27%"}, {"ticker": "ABEV", "name": "Ambev S.A.", "change": "-3.38%"}, {"ticker": "MRO", "name": "Marathon Oil Corporation", "change": "+9.68%"}, {"ticker": "ET", "name": "Energy Transfer LP", "change": "+8.43%"}, {"ticker": "GSAT", "name": "Globalstar, Inc.", "change": "-12.33%"}, {"ticker": "CAN", "name": "Canaan Inc.", "change": "-13.43%"}]}