{"timestamp": "Fri Jul 16 14:04:21 2021", "loosers": [{"ticker": "AMC", "name": "AMC Entertainment Holdings, Inc.", "change": "+0.28%"}, {"ticker": "AAPL", "name": "Apple Inc.", "change": "+0.31%"}, {"ticker": "SPCE", "name": "Virgin Galactic Holdings, Inc.", "change": "+0.23%"}, {"ticker": "MRNA", "name": "Moderna, Inc.", "change": "+9.48%"}, {"ticker": "NIO", "name": "NIO Inc.", "change": "-1.06%"}, {"ticker": "GE", "name": "General Electric Company", "change": "+0.71%"}, {"ticker": "ERIC", "name": "Telefonaktiebolaget LM Ericsson (publ)", "change": "-9.85%"}, {"ticker": "BAC", "name": "Bank of America Corporation", "change": "-0.52%"}, {"ticker": "WISH", "name": "ContextLogic Inc.", "change": "-0.50%"}, {"ticker": "AMD", "name": "Advanced Micro Devices, Inc.", "change": "+0.43%"}, {"ticker": "CCL", "name": "Carnival Corporation & plc", "change": "+0.23%"}, {"ticker": "RIG", "name": "Transocean Ltd.", "change": "-3.70%"}]}