{"timestamp": "Thu Jul 15 23:05:08 2021", "loosers": [{"ticker": "AMC", "name": "AMC Entertainment Holdings, Inc.", "change": "+7.69%"}, {"ticker": "AAPL", "name": "Apple Inc.", "change": "-0.45%"}, {"ticker": "SPCE", "name": "Virgin Galactic Holdings, Inc.", "change": "-4.02%"}, {"ticker": "NIO", "name": "NIO Inc.", "change": "+1.46%"}, {"ticker": "BAC", "name": "Bank of America Corporation", "change": "-0.08%"}, {"ticker": "GE", "name": "General Electric Company", "change": "-0.39%"}, {"ticker": "CCL", "name": "Carnival Corporation & plc", "change": "-2.79%"}, {"ticker": "F", "name": "Ford Motor Company", "change": "-1.68%"}, {"ticker": "WISH", "name": "ContextLogic Inc.", "change": "+3.17%"}, {"ticker": "ITUB", "name": "Ita\u00fa Unibanco Holding S.A.", "change": "-1.55%"}, {"ticker": "AMD", "name": "Advanced Micro Devices, Inc.", "change": "-2.38%"}, {"ticker": "NOK", "name": "Nokia Corporation", "change": "-1.54%"}, {"ticker": "AAL", "name": "American Airlines Group Inc.", "change": "-0.78%"}, {"ticker": "WFC", "name": "Wells Fargo & Company", "change": "+0.11%"}, {"ticker": "PLTR", "name": "Palantir Technologies Inc.", "change": "-0.42%"}, {"ticker": "NCLH", "name": "Norwegian Cruise Line Holdings Ltd.", "change": "-2.98%"}, {"ticker": "CLOV", "name": "Clover Health Investments, Corp.", "change": "-4.84%"}, {"ticker": "AZN", "name": "AstraZeneca PLC", "change": "-4.75%"}, {"ticker": "RLLCF", "name": "Rolls-Royce Holdings plc", "change": "+42.13%"}, {"ticker": "RIG", "name": "Transocean Ltd.", "change": "-7.12%"}, {"ticker": "BBD", "name": "Banco Bradesco S.A.", "change": "-1.83%"}, {"ticker": "T", "name": "AT&T Inc.", "change": "+0.60%"}, {"ticker": "TLRY", "name": "Tilray, Inc.", "change": "-4.06%"}, {"ticker": "ET", "name": "Energy Transfer LP", "change": "-2.88%"}, {"ticker": "TSM", "name": "Taiwan Semiconductor Manufacturing Company Limited", "change": "-5.51%"}]}